visaplan.tools-1.1-py2.7-nspkg.pth
visaplan/tools/classes.py
visaplan/tools/coding.py
visaplan/tools/files.py
visaplan/tools/html.py
visaplan/tools/http.py
visaplan/tools/sequences.py
visaplan/tools/times.py
visaplan.tools-1.1.dist-info/METADATA
visaplan.tools-1.1.dist-info/RECORD
visaplan.tools-1.1.dist-info/WHEEL
visaplan.tools-1.1.dist-info/namespace_packages.txt
visaplan.tools-1.1.dist-info/top_level.txt
