Metadata-Version: 2.1
Name: visaplan.tools
Version: 1.1
Summary: General Python tools
Home-page: https://pypi.org/project/visaplan.tools
Author: Tobias Herp
Author-email: tobias.herp@visaplan.com
License: UNKNOWN
Platform: UNKNOWN
Classifier: Programming Language :: Python
Classifier: Programming Language :: Python :: 2.7
Classifier: Intended Audience :: Developers
Classifier: Natural Language :: German
Classifier: Operating System :: OS Independent
Classifier: License :: OSI Approved :: Apache Software License
Requires-Dist: setuptools
